ytcompdl/__init__.py
ytcompdl/__main__.py
ytcompdl/errors.py
ytcompdl/ffmpeg_utils.py
ytcompdl/pytube_dl.py
ytcompdl/yt_comp_dl.py
ytcompdl-1.0.2.dist-info/LICENSE
ytcompdl-1.0.2.dist-info/METADATA
ytcompdl-1.0.2.dist-info/WHEEL
ytcompdl-1.0.2.dist-info/entry_points.txt
ytcompdl-1.0.2.dist-info/top_level.txt
ytcompdl-1.0.2.dist-info/RECORD
