Metadata-Version: 2.1
Name: ytcompdl
Version: 1.0.2
Summary: Script to download and segment youtube videos automatically.
Home-page: https://github.com/koisland/YtCompDL
Author: Keith Oshima
Author-email: koshima789@gmail.com
License: MIT
Classifier: License :: OSI Approved :: MIT License
License-File: LICENSE
Requires-Dist: cachetools (==4.2.4)
Requires-Dist: certifi (==2021.10.8)
Requires-Dist: charset-normalizer (==2.0.7)
Requires-Dist: colorama (==0.4.4)
Requires-Dist: ffmpeg-python (==0.2.0)
Requires-Dist: future (==0.18.2)
Requires-Dist: google-api-core (==2.2.2)
Requires-Dist: google-api-python-client (==2.29.0)
Requires-Dist: google-auth (==2.3.3)
Requires-Dist: google-auth-httplib2 (==0.1.0)
Requires-Dist: googleapis-common-protos (==1.53.0)
Requires-Dist: httplib2 (==0.20.2)
Requires-Dist: idna (==3.3)
Requires-Dist: protobuf (==3.19.1)
Requires-Dist: pyasn1 (==0.4.8)
Requires-Dist: pyasn1-modules (==0.2.8)
Requires-Dist: pyparsing (==3.0.4)
Requires-Dist: python-dotenv (==0.20.0)
Requires-Dist: pytube (==12.1.0)
Requires-Dist: pyyaml (==6.0)
Requires-Dist: requests (==2.26.0)
Requires-Dist: rsa (==4.7.2)
Requires-Dist: six (==1.16.0)
Requires-Dist: tqdm (==4.62.3)
Requires-Dist: uritemplate (==4.1.1)
Requires-Dist: urllib3 (==1.26.7)
